sidcli/__init__.py
sidcli/sidcli.py
sidcli-0.2.dist-info/METADATA
sidcli-0.2.dist-info/WHEEL
sidcli-0.2.dist-info/entry_points.txt
sidcli-0.2.dist-info/top_level.txt
sidcli-0.2.dist-info/RECORD
