Metadata-Version: 2.1
Name: sidcli
Version: 0.2
Requires-Dist: boto3
Requires-Dist: click
